SASOupstox/__init__.py
SASOupstox/upstox.py
UpstoxWithoutAPI/__init__.py
UpstoxWithoutAPI/upstox.py
aliceblue_fetch_data/__init__.py
aliceblue_fetch_data/alice.py
copytrading_upstox/__init__.py
copytrading_upstox/upstox.py
copytrading_upstox_withoutapi/__init__.py
copytrading_upstox_withoutapi/upstox.py
fyers_withoutapi/__init__.py
fyers_withoutapi/fyers.py
upstox_withoutapi/__init__.py
upstox_withoutapi/upstox.py
zerodha_without_api/__init__.py
zerodha_without_api/zerodha.py
UpstoxWithoutAPI-0.0.1.dist-info/LICENSE
UpstoxWithoutAPI-0.0.1.dist-info/METADATA
UpstoxWithoutAPI-0.0.1.dist-info/WHEEL
UpstoxWithoutAPI-0.0.1.dist-info/top_level.txt
UpstoxWithoutAPI-0.0.1.dist-info/RECORD
